remote_cmd/__init__.py
remote_cmd/cmd.py
remote_cmd-0.1.2.dist-info/LICENSE
remote_cmd-0.1.2.dist-info/METADATA
remote_cmd-0.1.2.dist-info/WHEEL
remote_cmd-0.1.2.dist-info/top_level.txt
remote_cmd-0.1.2.dist-info/RECORD
