Metadata-Version: 2.2
Name: remote_cmd
Version: 0.1.2
Summary: A small package to create a remote command line for testing and automation purposes
Author-email: Aad3b435 <aad3b435@gmail.com>
License: MIT License
Classifier: Programming Language :: Python :: 3
Classifier: Operating System :: OS Independent
Requires-Python: >=3.8
License-File: LICENSE
Requires-Dist: websockets
